Metadata-Version: 2.1
Name: finitelycomputable-helloworld-quart
Version: 24.7
Summary: A hello_world implementation in Quart
Author-email: Samuel Newbold <sam@rwsh.org>
License: AGPL-3.0-only
Project-URL: Documentation, https://github.com/thrasymache/microsites
Project-URL: Source, https://github.com/thrasymache/microsites
Project-URL: Gitlab, https://gitlab.com/thrasymache/microsites
Project-URL: sourcehut, https://git.sr.ht/~thrasymache/finitelycomputable-microsites
Project-URL: NotABug, https://notabug.org/thrasymache/finitelycomputable-microsites
Classifier: Development Status :: 3 - Alpha
Classifier: Environment :: Web Environment
Classifier: Intended Audience :: Developers
Classifier: License :: OSI Approved :: GNU Affero General Public License v3
Classifier: Operating System :: OS Independent
Classifier: Programming Language :: Python
Classifier: Programming Language :: Python :: 3
Classifier: Programming Language :: Python :: 3.8
Classifier: Programming Language :: Python :: 3.9
Classifier: Programming Language :: Python :: 3.10
Classifier: Programming Language :: Python :: 3.11
Classifier: Topic :: Internet :: WWW/HTTP
Classifier: Topic :: Internet :: WWW/HTTP :: Dynamic Content
Requires-Python: >=3.8
Requires-Dist: Quart ~=0.19
Provides-Extra: tests
Requires-Dist: pytest ; extra == 'tests'
Requires-Dist: pytest-env ; extra == 'tests'
Requires-Dist: finitelycomputable-tests ; extra == 'tests'
Requires-Dist: pytest-asyncio ; extra == 'tests'
